setup.py
distributions/Binomialdistribution.py
distributions/Gaussiandistribution.py
distributions/Generaldistribution.py
distributions/__init__.py
nj11_distributions.egg-info/PKG-INFO
nj11_distributions.egg-info/SOURCES.txt
nj11_distributions.egg-info/dependency_links.txt
nj11_distributions.egg-info/not-zip-safe
nj11_distributions.egg-info/top_level.txt